nuid-0.0.1.dist-info/METADATA
nuid-0.0.1.dist-info/WHEEL
nuid-0.0.1.dist-info/license_files/LICENSE
nuid/nuid.pyi
nuid/__init__.py
nuid/py.typed
nuid/nuid.cpython-311-darwin.so
nuid-0.0.1.dist-info/RECORD
