Metadata-Version: 2.3
Name: nuid
Version: 0.0.1
Classifier: Development Status :: 5 - Production/Stable
Classifier: Intended Audience :: Developers
Classifier: License :: OSI Approved :: Apache Software License
Classifier: License :: OSI Approved :: MIT License
Classifier: Operating System :: MacOS
Classifier: Operating System :: Microsoft :: Windows
Classifier: Operating System :: POSIX :: Linux
Classifier: Programming Language :: Python :: 3
Classifier: Programming Language :: Python :: 3.8
Classifier: Programming Language :: Python :: 3.9
Classifier: Programming Language :: Python :: 3.10
Classifier: Programming Language :: Python :: 3.11
Classifier: Programming Language :: Python :: 3.12
Classifier: Programming Language :: Python :: 3.13
Classifier: Programming Language :: Python :: Implementation :: CPython
Classifier: Programming Language :: Python
Classifier: Programming Language :: Rust
Classifier: Typing :: Typed
License-File: LICENSE
Summary: A highly performant unique identifier generator.
Keywords: nuid,guid,uuid
Author: sheldy <chikibamtioma@gmail.com>
Author-email: sheldy <chikibamtioma@gmail.com>
License: Apache-2.0
Requires-Python: >=3.8
Project-URL: Source Code, https://github.com/sheldygg/py-nuid.git
